{
  "strings": {
    "WINSLOW_MAP_FORLORNWRECKAGE_TITLE": "Скорботні уламки",
    "WINSLOW_MAP_FORLORNWRECKAGE_SUBTITLE": "Покинуті рештки UES «Contact Light»",
    "WINSLOW_MAP_FORLORNWRECKAGE_BAZAAR_SEER": "<style=cWorldEvent>Ви мрієте про вічну мерзлоту й розбите скло...</style>",
    "WINSLOW_MAP_FORLORNWRECKAGE_LORE": "<style=cMono> \nВітаємо в DataScraper (v3.1.54 – модифікована версія)\n$ Збір даних... готово. \n$ Аналіз... готово. \n$ Пошук відповідних даних... готово. \n$ Збір модифікованих баз... готово.\nОперацію завершено!\nВиводимо транскрипції локального аудіо...\n</style>\n\n<style=cMono>День 5</style>\n<style=cMono>$ Початок передачі</style>\nМи знайшли останні залишки уламків Contact Light... Джеймс *кудись* пішов, та сказав, що скоро повернеться, тож я вирішив влаштувати привал під одним з уламків; Я б відзвітував Safe Travels алееее мій передавач під час тої сутички у долині просто розтрощило.. О! Джеймс повернувся окей ти мо-\n<style=cMono>$ Кінець передачі</style>\n\n<style=cMono>День 6</style>\n<style=cMono>$ Початок передачі</style>\nГаразд- отож, мене й Джеймса неабияк відгамселили. Ми перемістили наш табір за один із вантажних відсіків та змогли надіслати Safe Travels сигнал 4 дні тому але ми досі не отримали відповіді.. з часу надсилання все що ми отримали це спотворений шум і лиш інколи якісь віддалені голоси. Найчистіший сигнал, що нам вдалось перехопити говорив про якийсь сигнал лиха і... любов? Не знаю, що це в біса значить, але поки ми перевертали з ніг на голову вантажні відсіки мені вдалось надибати якийсь типу журнал, але його майже неможливо нормально читати через те, скільки він часу тут провалявся... Але це надто цікаво, тому я спробую розшифрувати цю писанину.\n<style=cMono>$ Кінець передачі</style>\n\n<style=cMono>День 8</style>\n<style=cMono>$ Початок передачі</style>\nЦейво, щодо журналу, мені вдалось розшифрувати більшу частину і мені здається, що тут мова про он ту величезну споруду, що вдалині попід горою? Давай прочитаю трохи. «Цей міст все простягається вдалечінь, без кінця... але це хоча б міст. У цій хуртовині і гірському тумані видимість не більше двох метрів, навіть із моїми ліхтарями.» Ти ба. Цьому хлопчині точно не пощастило... Так от, тут ще й декілька непоганих фотографій деяких із тутешніх істот, таких, що я ще навіть і не бачив! Ну і дякувати богу! Тут типу фото якогось вогняного звіра..? Ніби щось прямо з якихось міфів...\n<style=cMono>$ Кінець передачі</style>\n\n<style=cMono>Кінець транскрипції локального аудіо.\n</style>",
    "UNLOCKABLE_LOG_STAGES_FWRECKAGE_SCENE": "Запис про оточення: Скорботні уламки"
  }
}
